[{"id":"1","variable":"montoTotal","titulo":"Monto total de compras adjudicadas (Del 1/01/2020 al 30/05/2020)","descripcion":"Monto Total de compras adjudicadas (Del 1/01/2020 al 30/05/2020)","Unidad":"1,148,697,063.590","dimension":"quetzales"},{"id":"2","variable":"concursos","titulo":"Concursos Realizados (Del 1/01/2020 al 30/05/2020)","descripcion":"Total de concursos realizados","Unidad":"13,078","dimension":"concursos"},{"id":"3","variable":"concursosTerminados","titulo":"Adjudicados Terminados (Del 1/01/2020 al 30/05/2020)","descripcion":"Terminados adjudicados","Unidad":"7,848","dimension":"concursos"},{"id":"4","variable":"concursosEvaluacion","titulo":"","descripcion":"En evaluación","Unidad":"843","dimension":"concursos"},{"id":"5","variable":"concursosAnulados","titulo":"","descripcion":"Finalizados anulados","Unidad":"2,457","dimension":"concursos"},{"id":"6","variable":"ConcursosDesiertos","titulo":"","descripcion":"Finalizados desiertos","Unidad":"1,656","dimension":"concursos"},{"id":"7","variable":"concursosVigente","titulo":"Concursos vigentes (Del 1/01/2020 al 30/05/2020)","descripcion":"Concursos vigentes","Unidad":"274","dimension":"concursos"}]